setup.py
rastelyvista/__init__.py
rastelyvista/export.py
rastelyvista.egg-info/PKG-INFO
rastelyvista.egg-info/SOURCES.txt
rastelyvista.egg-info/dependency_links.txt
rastelyvista.egg-info/requires.txt
rastelyvista.egg-info/top_level.txt